{
  "filename": "kedl.xml",
  "icon": "asset_icon.jpg",
  "id": "com.nexstreaming.kinemaster.travel.accent",
  "label": {
    "pt":     "Viagem - Enfatizado",
    "ja":     "旅行 - アクセント",
    "fr":     "Voyage - Accent",
    "zh-CN":  "旅行 - 强调",
    "ko-KR":  "여행 - 엑센트",
    "zh-TW":  "旅行 - 強調",
    "en":     "Travel - Accent",
    "zh-HK":  "旅行 - 強調",
    "de-DE":  "Reisen - Akzent",
    "ru":     "Путешествие - Акцент",
    "es":     "Viajes - Énfasis",
    "ar":     "سفر - لهجة"
  },
  "type": "nex.kedl",
  "hidden": false
}